Metadata-Version: 2.1
Name: Topsis-Keshav-102017064
Version: 0.0.1
Summary: This package performs the topsis(multiple criterion decision making) on a pandas dataframe and return the rank and topsis score.
Home-page: https://github.com/keshavgarg23/Topsis-Keshav-102017064
Author: Keshav Garg
Author-email: gkeshav2309@gmail.com
License: MIT
Download-URL: https://github.com/keshavgarg23/Topsis-Keshav-102017064/archive/refs/tags/v.01.tar.gz
Keywords: TOPSIS,MCDM,DECISION,MAKING
Platform: UNKNOWN
Classifier: Development Status :: 3 - Alpha
Classifier: Intended Audience :: Developers
Classifier: Topic :: Software Development :: Build Tools
Classifier: License :: OSI Approved :: MIT License
Classifier: Programming Language :: Python :: 3
Classifier: Programming Language :: Python :: 3.4
Classifier: Programming Language :: Python :: 3.5
Classifier: Programming Language :: Python :: 3.6
License-File: LICENSE
Requires-Dist: numpy
Requires-Dist: pandas
